exaparser/__init__.py
exaparser/_version.py
exaparser/cli.py
exaparser/config.py
exaparser/enums.py
exaparser/utils.py
exaparser/data/__init__.py
exaparser/data/factory.py
exaparser/data/handlers/__init__.py
exaparser/data/handlers/disk.py
exaparser/data/handlers/exabyte.py
exaparser/data/handlers/stdout.py
exaparser/job/__init__.py
exaparser/job/compute/__init__.py
exaparser/job/compute/factory.py
exaparser/job/compute/managers/__init__.py
exaparser/job/compute/managers/pbs.py
exaparser/job/compute/managers/slurm.py
exaparser/workflow/__init__.py
exaparser/workflow/subworkflow.py
exaparser/workflow/workflow.py
exaparser/workflow/units/__init__.py
exaparser/workflow/units/factory.py
exaparser/workflow/units/subworkflow.py
exaparser/workflow/units/execution/__init__.py
exaparser/workflow/units/execution/modeling/__init__.py
exaparser/workflow/units/execution/modeling/espresso.py
exaparser/workflow/units/execution/modeling/vasp.py
exaparser/workflow/units/execution/scripting/__init__.py
exaparser/workflow/units/execution/scripting/shell.py
exaparser/workflow/units/execution/scripting/shell_with_results.py
exaparser-2024.2.16.post2.dist-info/LICENSE
exaparser-2024.2.16.post2.dist-info/METADATA
exaparser-2024.2.16.post2.dist-info/WHEEL
exaparser-2024.2.16.post2.dist-info/entry_points.txt
exaparser-2024.2.16.post2.dist-info/top_level.txt
exaparser-2024.2.16.post2.dist-info/RECORD
