Metadata-Version: 2.1
Name: exaparser
Version: 2024.2.16.post2
Summary: Exabyte Parser
Home-page: https://github.com/Exabyte-io/exaparser
Author: Exabyte Inc.
Author-email: info@exabyte.io
Classifier: Programming Language :: Python
Classifier: Development Status :: 3 - Alpha
Classifier: Topic :: Software Development
Requires-Python: >=3.6
License-File: LICENSE
Requires-Dist: exabyte-api-client >=2024.2.2.post1
Requires-Dist: express-py >=2024.2.2.post2
Requires-Dist: requests >=2.26.0
Provides-Extra: test
Requires-Dist: coverage[toml] >=5.3 ; extra == 'test'
Requires-Dist: mock >=1.3.0 ; extra == 'test'
Requires-Dist: numpy >=1.17.3 ; extra == 'test'
